pypagination/__init__.py
pypagination-0.0.3.dist-info/LICENSE.txt
pypagination-0.0.3.dist-info/METADATA
pypagination-0.0.3.dist-info/WHEEL
pypagination-0.0.3.dist-info/top_level.txt
pypagination-0.0.3.dist-info/RECORD
