Metadata-Version: 2.1
Name: pypagination
Version: 0.0.3
Summary: A small library to paginate through json objects
Home-page: https://github.com/mishal9/pypagination/issues
Author: Mishal Shah
Author-email: mshah31@asu.edu
License: UNKNOWN
Platform: UNKNOWN
Classifier: Programming Language :: Python :: 2.7
Classifier: Programming Language :: Python :: 3
Classifier: License :: OSI Approved :: MIT License
Classifier: Operating System :: OS Independent
Requires-Python: >=2.6, !=3.0.*, !=3.1.*, !=3.2.*, <4
